{
  "id": "6262f36a-1d06-48a9-a673-9b499fa28a52",
  "realm": "master",
  "displayName": "Keycloak",
  "displayNameHtml": "<div class=\"kc-logo-text\"><span>Keycloak</span></div>",
  "notBefore": 0,
  "defaultSignatureAlgorithm": "RS256",
  "revokeRefreshToken": false,
  "refreshTokenMaxReuse": 0,
  "accessTokenLifespan": 60,
  "accessTokenLifespanForImplicitFlow": 900,
  "ssoSessionIdleTimeout": 1800,
  "ssoSessionMaxLifespan": 36000,
  "ssoSessionIdleTimeoutRememberMe": 0,
  "ssoSessionMaxLifespanRememberMe": 0,
  "offlineSessionIdleTimeout": 2592000,
  "offlineSessionMaxLifespanEnabled": false,
  "offlineSessionMaxLifespan": 5184000,
  "clientSessionIdleTimeout": 0,
  "clientSessionMaxLifespan": 0,
  "clientOfflineSessionIdleTimeout": 0,
  "clientOfflineSessionMaxLifespan": 0,
  "accessCodeLifespan": 60,
  "accessCodeLifespanUserAction": 300,
  "accessCodeLifespanLogin": 1800,
  "actionTokenGeneratedByAdminLifespan": 43200,
  "actionTokenGeneratedByUserLifespan": 300,
  "oauth2DeviceCodeLifespan": 600,
  "oauth2DevicePollingInterval": 5,
  "enabled": true,
  "sslRequired": "external",
  "registrationAllowed": false,
  "registrationEmailAsUsername": false,
  "rememberMe": false,
  "verifyEmail": false,
  "loginWithEmailAllowed": true,
  "duplicateEmailsAllowed": false,
  "resetPasswordAllowed": false,
  "editUsernameAllowed": false,
  "bruteForceProtected": false,
  "permanentLockout": false,
  "maxTemporaryLockouts": 0,
  "bruteForceStrategy": "MULTIPLE",
  "maxFailureWaitSeconds": 900,
  "minimumQuickLoginWaitSeconds": 60,
  "waitIncrementSeconds": 60,
  "quickLoginCheckMilliSeconds": 1000,
  "maxDeltaTimeSeconds": 43200,
  "failureFactor": 30,
  "roles": {
    "realm": [
      {
        "id": "c690bdff-ba20-41a0-a8ac-668b1dae0fe5",
        "name": "admin",
        "description": "${role_admin}",
        "composite": true,
        "composites": {
          "realm": [
            "create-realm"
          ],
          "client": {
            "master-realm": [
              "create-client",
              "query-clients",
              "manage-events",
              "view-users",
              "view-authorization",
              "manage-realm",
              "view-events",
              "query-realms",
              "manage-clients",
              "manage-identity-providers",
              "view-identity-providers",
              "query-groups",
              "manage-authorization",
              "query-users",
              "manage-users",
              "view-realm",
              "view-clients",
              "impersonation"
            ]
          }
        },
        "clientRole": false,
        "containerId": "6262f36a-1d06-48a9-a673-9b499fa28a52",
        "attributes": {}
      },
      {
        "id": "c8642a7d-ac29-49f0-9b93-70cd191c4c8b",
        "name": "uma_authorization",
        "description": "${role_uma_authorization}",
        "composite": false,
        "clientRole": false,
        "containerId": "6262f36a-1d06-48a9-a673-9b499fa28a52",
        "attributes": {}
      },
      {
        "id": "36a6e4b7-73c0-45d3-a73c-de332d99f77c",
        "name": "create-realm",
        "description": "${role_create-realm}",
        "composite": false,
        "clientRole": false,
        "containerId": "6262f36a-1d06-48a9-a673-9b499fa28a52",
        "attributes": {}
      },
      {
        "id": "297e944a-900c-479e-a5d3-3d1de584d886",
        "name": "default-roles-master",
        "description": "${role_default-roles}",
        "composite": true,
        "composites": {
          "realm": [
            "offline_access",
            "uma_authorization"
          ],
          "client": {
            "account": [
              "manage-account",
              "view-profile"
            ]
          }
        },
        "clientRole": false,
        "containerId": "6262f36a-1d06-48a9-a673-9b499fa28a52",
        "attributes": {}
      },
      {
        "id": "ca415717-fb45-431b-b575-a65ba62d0e21",
        "name": "offline_access",
        "description": "${role_offline-access}",
        "composite": false,
        "clientRole": false,
        "containerId": "6262f36a-1d06-48a9-a673-9b499fa28a52",
        "attributes": {}
      }
    ],
    "client": {
      "security-admin-console": [],
      "admin-cli": [],
      "account-console": [],
      "broker": [
        {
          "id": "d0c4ee23-0d51-42cf-9ab0-46e47ec33acf",
          "name": "read-token",
          "description": "${role_read-token}",
          "composite": false,
          "clientRole": true,
          "containerId": "d2ba0100-17be-4c6b-8540-ebaa22b6e2e8",
          "attributes": {}
        }
      ],
      "master-realm": [
        {
          "id": "34f83bb3-fda9-453c-81b8-dba429e56c3d",
          "name": "create-client",
          "description": "${role_create-client}",
          "composite": false,
          "clientRole": true,
          "containerId": "4ba9c175-bf74-43db-9cf6-e1c1052415c6",
          "attributes": {}
        },
        {
          "id": "ead21988-12ad-4d81-bb19-eccf0923404a",
          "name": "query-clients",
          "description": "${role_query-clients}",
          "composite": false,
          "clientRole": true,
          "containerId": "4ba9c175-bf74-43db-9cf6-e1c1052415c6",
          "attributes": {}
        },
        {
          "id": "f4cfc650-cb5d-4f91-8e18-3d5a493929ba",
          "name": "manage-events",
          "description": "${role_manage-events}",
          "composite": false,
          "clientRole": true,
          "containerId": "4ba9c175-bf74-43db-9cf6-e1c1052415c6",
          "attributes": {}
        },
        {
          "id": "e542afca-a40f-425d-8efa-316c4f658833",
          "name": "view-users",
          "description": "${role_view-users}",
          "composite": true,
          "composites": {
            "client": {
              "master-realm": [
                "query-users",
                "query-groups"
              ]
            }
          },
          "clientRole": true,
          "containerId": "4ba9c175-bf74-43db-9cf6-e1c1052415c6",
          "attributes": {}
        },
        {
          "id": "2ef6f8f7-a27c-48f6-bebc-46e56812e7af",
          "name": "manage-realm",
          "description": "${role_manage-realm}",
          "composite": false,
          "clientRole": true,
          "containerId": "4ba9c175-bf74-43db-9cf6-e1c1052415c6",
          "attributes": {}
        },
        {
          "id": "25429206-9173-49d6-9cfe-82686800ee28",
          "name": "view-authorization",
          "description": "${role_view-authorization}",
          "composite": false,
          "clientRole": true,
          "containerId": "4ba9c175-bf74-43db-9cf6-e1c1052415c6",
          "attributes": {}
        },
        {
          "id": "fb43983c-5fc5-4eec-b574-c26114d5bd83",
          "name": "query-realms",
          "description": "${role_query-realms}",
          "composite": false,
          "clientRole": true,
          "containerId": "4ba9c175-bf74-43db-9cf6-e1c1052415c6",
          "attributes": {}
        },
        {
          "id": "72e4a8db-df5a-4547-b6a5-778695de5e7c",
          "name": "view-events",
          "description": "${role_view-events}",
          "composite": false,
          "clientRole": true,
          "containerId": "4ba9c175-bf74-43db-9cf6-e1c1052415c6",
          "attributes": {}
        },
        {
          "id": "32913948-3775-4be3-bff8-729e2dcf9cc2",
          "name": "manage-clients",
          "description": "${role_manage-clients}",
          "composite": false,
          "clientRole": true,
          "containerId": "4ba9c175-bf74-43db-9cf6-e1c1052415c6",
          "attributes": {}
        },
        {
          "id": "42451660-6bf0-408b-9a12-547700c9e727",
          "name": "manage-identity-providers",
          "description": "${role_manage-identity-providers}",
          "composite": false,
          "clientRole": true,
          "containerId": "4ba9c175-bf74-43db-9cf6-e1c1052415c6",
          "attributes": {}
        },
        {
          "id": "a2dce01f-b8ba-4307-ad49-cab689ca2223",
          "name": "query-groups",
          "description": "${role_query-groups}",
          "composite": false,
          "clientRole": true,
          "containerId": "4ba9c175-bf74-43db-9cf6-e1c1052415c6",
          "attributes": {}
        },
        {
          "id": "6f776851-7fc9-4ae4-a683-5d24bc53e368",
          "name": "view-identity-providers",
          "description": "${role_view-identity-providers}",
          "composite": false,
          "clientRole": true,
          "containerId": "4ba9c175-bf74-43db-9cf6-e1c1052415c6",
          "attributes": {}
        },
        {
          "id": "423581d1-2ad6-4bf3-9611-c9af0db9465c",
          "name": "manage-authorization",
          "description": "${role_manage-authorization}",
          "composite": false,
          "clientRole": true,
          "containerId": "4ba9c175-bf74-43db-9cf6-e1c1052415c6",
          "attributes": {}
        },
        {
          "id": "8ceba391-6b9c-4dff-8fee-758597e9716e",
          "name": "manage-users",
          "description": "${role_manage-users}",
          "composite": false,
          "clientRole": true,
          "containerId": "4ba9c175-bf74-43db-9cf6-e1c1052415c6",
          "attributes": {}
        },
        {
          "id": "01783e1d-fe27-4f13-b8a8-e0ce00430085",
          "name": "query-users",
          "description": "${role_query-users}",
          "composite": false,
          "clientRole": true,
          "containerId": "4ba9c175-bf74-43db-9cf6-e1c1052415c6",
          "attributes": {}
        },
        {
          "id": "d3028476-0308-4a09-a640-67f81ffb3421",
          "name": "view-realm",
          "description": "${role_view-realm}",
          "composite": false,
          "clientRole": true,
          "containerId": "4ba9c175-bf74-43db-9cf6-e1c1052415c6",
          "attributes": {}
        },
        {
          "id": "fd67e0a1-fedd-45c4-bf85-fa7180d46f55",
          "name": "view-clients",
          "description": "${role_view-clients}",
          "composite": true,
          "composites": {
            "client": {
              "master-realm": [
                "query-clients"
              ]
            }
          },
          "clientRole": true,
          "containerId": "4ba9c175-bf74-43db-9cf6-e1c1052415c6",
          "attributes": {}
        },
        {
          "id": "cd5f5f99-3556-4830-bb80-36d67c8d4173",
          "name": "impersonation",
          "description": "${role_impersonation}",
          "composite": false,
          "clientRole": true,
          "containerId": "4ba9c175-bf74-43db-9cf6-e1c1052415c6",
          "attributes": {}
        }
      ],
      "internet-shop": [],
      "account": [
        {
          "id": "3a85c17e-ab1a-49b2-954b-6275bac65c7a",
          "name": "manage-consent",
          "description": "${role_manage-consent}",
          "composite": true,
          "composites": {
            "client": {
              "account": [
                "view-consent"
              ]
            }
          },
          "clientRole": true,
          "containerId": "73ac9a56-0ea6-4b29-9ae1-a649c4dde286",
          "attributes": {}
        },
        {
          "id": "544e7dc1-5586-4c7f-9a3c-4e606d71200d",
          "name": "view-applications",
          "description": "${role_view-applications}",
          "composite": false,
          "clientRole": true,
          "containerId": "73ac9a56-0ea6-4b29-9ae1-a649c4dde286",
          "attributes": {}
        },
        {
          "id": "fe51abca-9dd8-4b5b-9987-4032f68f3ca3",
          "name": "manage-account",
          "description": "${role_manage-account}",
          "composite": true,
          "composites": {
            "client": {
              "account": [
                "manage-account-links"
              ]
            }
          },
          "clientRole": true,
          "containerId": "73ac9a56-0ea6-4b29-9ae1-a649c4dde286",
          "attributes": {}
        },
        {
          "id": "b01bc59e-0264-465e-af55-9052ffbc5942",
          "name": "view-consent",
          "description": "${role_view-consent}",
          "composite": false,
          "clientRole": true,
          "containerId": "73ac9a56-0ea6-4b29-9ae1-a649c4dde286",
          "attributes": {}
        },
        {
          "id": "cc120e61-7b39-4a0b-a6cd-9e7d548ba189",
          "name": "delete-account",
          "description": "${role_delete-account}",
          "composite": false,
          "clientRole": true,
          "containerId": "73ac9a56-0ea6-4b29-9ae1-a649c4dde286",
          "attributes": {}
        },
        {
          "id": "d0a758fe-d3ae-4fee-97b1-50e386de24ec",
          "name": "view-profile",
          "description": "${role_view-profile}",
          "composite": false,
          "clientRole": true,
          "containerId": "73ac9a56-0ea6-4b29-9ae1-a649c4dde286",
          "attributes": {}
        },
        {
          "id": "e8922d33-198d-4df2-9b66-151b90dff7c0",
          "name": "view-groups",
          "description": "${role_view-groups}",
          "composite": false,
          "clientRole": true,
          "containerId": "73ac9a56-0ea6-4b29-9ae1-a649c4dde286",
          "attributes": {}
        },
        {
          "id": "714edd57-657a-4f91-a882-0f2a9bae3f80",
          "name": "manage-account-links",
          "description": "${role_manage-account-links}",
          "composite": false,
          "clientRole": true,
          "containerId": "73ac9a56-0ea6-4b29-9ae1-a649c4dde286",
          "attributes": {}
        }
      ]
    }
  },
  "groups": [],
  "defaultRole": {
    "id": "297e944a-900c-479e-a5d3-3d1de584d886",
    "name": "default-roles-master",
    "description": "${role_default-roles}",
    "composite": true,
    "clientRole": false,
    "containerId": "6262f36a-1d06-48a9-a673-9b499fa28a52"
  },
  "requiredCredentials": [
    "password"
  ],
  "otpPolicyType": "totp",
  "otpPolicyAlgorithm": "HmacSHA1",
  "otpPolicyInitialCounter": 0,
  "otpPolicyDigits": 6,
  "otpPolicyLookAheadWindow": 1,
  "otpPolicyPeriod": 30,
  "otpPolicyCodeReusable": false,
  "otpSupportedApplications": [
    "totpAppFreeOTPName",
    "totpAppGoogleName",
    "totpAppMicrosoftAuthenticatorName"
  ],
  "localizationTexts": {},
  "webAuthnPolicyRpEntityName": "keycloak",
  "webAuthnPolicySignatureAlgorithms": [
    "ES256",
    "RS256"
  ],
  "webAuthnPolicyRpId": "",
  "webAuthnPolicyAttestationConveyancePreference": "not specified",
  "webAuthnPolicyAuthenticatorAttachment": "not specified",
  "webAuthnPolicyRequireResidentKey": "not specified",
  "webAuthnPolicyUserVerificationRequirement": "not specified",
  "webAuthnPolicyCreateTimeout": 0,
  "webAuthnPolicyAvoidSameAuthenticatorRegister": false,
  "webAuthnPolicyAcceptableAaguids": [],
  "webAuthnPolicyExtraOrigins": [],
  "webAuthnPolicyPasswordlessRpEntityName": "keycloak",
  "webAuthnPolicyPasswordlessSignatureAlgorithms": [
    "ES256",
    "RS256"
  ],
  "webAuthnPolicyPasswordlessRpId": "",
  "webAuthnPolicyPasswordlessAttestationConveyancePreference": "not specified",
  "webAuthnPolicyPasswordlessAuthenticatorAttachment": "not specified",
  "webAuthnPolicyPasswordlessRequireResidentKey": "not specified",
  "webAuthnPolicyPasswordlessUserVerificationRequirement": "not specified",
  "webAuthnPolicyPasswordlessCreateTimeout": 0,
  "webAuthnPolicyPasswordlessAvoidSameAuthenticatorRegister": false,
  "webAuthnPolicyPasswordlessAcceptableAaguids": [],
  "webAuthnPolicyPasswordlessExtraOrigins": [],
  "users": [
    {
      "id": "4d4ce41f-be6b-426f-b64f-749067c47f5b",
      "username": "service-account-internet-shop",
      "emailVerified": false,
      "createdTimestamp": 1760132668314,
      "enabled": true,
      "totp": false,
      "serviceAccountClientId": "internet-shop",
      "disableableCredentialTypes": [],
      "requiredActions": [],
      "notBefore": 0,
      "groups": []
    }
  ],
  "scopeMappings": [
    {
      "clientScope": "offline_access",
      "roles": [
        "offline_access"
      ]
    }
  ],
  "clientScopeMappings": {
    "account": [
      {
        "client": "account-console",
        "roles": [
          "manage-account",
          "view-groups"
        ]
      }
    ]
  },
  "clients": [
    {
      "id": "73ac9a56-0ea6-4b29-9ae1-a649c4dde286",
      "clientId": "account",
      "name": "${client_account}",
      "rootUrl": "${authBaseUrl}",
      "baseUrl": "/realms/master/account/",
      "surrogateAuthRequired": false,
      "enabled": true,
      "alwaysDisplayInConsole": false,
      "clientAuthenticatorType": "client-secret",
      "redirectUris": [
        "/realms/master/account/*"
      ],
      "webOrigins": [],
      "notBefore": 0,
      "bearerOnly": false,
      "consentRequired": false,
      "standardFlowEnabled": true,
      "implicitFlowEnabled": false,
      "directAccessGrantsEnabled": false,
      "serviceAccountsEnabled": false,
      "publicClient": true,
      "frontchannelLogout": false,
      "protocol": "openid-connect",
      "attributes": {
        "realm_client": "false",
        "post.logout.redirect.uris": "+"
      },
      "authenticationFlowBindingOverrides": {},
      "fullScopeAllowed": false,
      "nodeReRegistrationTimeout": 0,
      "defaultClientScopes": [
        "web-origins",
        "acr",
        "roles",
        "profile",
        "basic",
        "email"
      ],
      "optionalClientScopes": [
        "address",
        "phone",
        "organization",
        "offline_access",
        "microprofile-jwt"
      ]
    },
    {
      "id": "e32abd74-5ea3-4e98-a8c3-058903d05ed0",
      "clientId": "account-console",
      "name": "${client_account-console}",
      "rootUrl": "${authBaseUrl}",
      "baseUrl": "/realms/master/account/",
      "surrogateAuthRequired": false,
      "enabled": true,
      "alwaysDisplayInConsole": false,
      "clientAuthenticatorType": "client-secret",
      "redirectUris": [
        "/realms/master/account/*"
      ],
      "webOrigins": [],
      "notBefore": 0,
      "bearerOnly": false,
      "consentRequired": false,
      "standardFlowEnabled": true,
      "implicitFlowEnabled": false,
      "directAccessGrantsEnabled": false,
      "serviceAccountsEnabled": false,
      "publicClient": true,
      "frontchannelLogout": false,
      "protocol": "openid-connect",
      "attributes": {
        "realm_client": "false",
        "post.logout.redirect.uris": "+",
        "pkce.code.challenge.method": "S256"
      },
      "authenticationFlowBindingOverrides": {},
      "fullScopeAllowed": false,
      "nodeReRegistrationTimeout": 0,
      "protocolMappers": [
        {
          "id": "395e4b86-3f4b-44d1-bc18-3c833ccef193",
          "name": "audience resolve",
          "protocol": "openid-connect",
          "protocolMapper": "oidc-audience-resolve-mapper",
          "consentRequired": false,
          "config": {}
        }
      ],
      "defaultClientScopes": [
        "web-origins",
        "acr",
        "roles",
        "profile",
        "basic",
        "email"
      ],
      "optionalClientScopes": [
        "address",
        "phone",
        "organization",
        "offline_access",
        "microprofile-jwt"
      ]
    },
    {
      "id": "448bfd2b-cb87-44c9-8e90-0e4b22fc5ca4",
      "clientId": "admin-cli",
      "name": "${client_admin-cli}",
      "surrogateAuthRequired": false,
      "enabled": true,
      "alwaysDisplayInConsole": false,
      "clientAuthenticatorType": "client-secret",
      "redirectUris": [],
      "webOrigins": [],
      "notBefore": 0,
      "bearerOnly": false,
      "consentRequired": false,
      "standardFlowEnabled": false,
      "implicitFlowEnabled": false,
      "directAccessGrantsEnabled": true,
      "serviceAccountsEnabled": false,
      "publicClient": true,
      "frontchannelLogout": false,
      "protocol": "openid-connect",
      "attributes": {
        "realm_client": "false",
        "client.use.lightweight.access.token.enabled": "true"
      },
      "authenticationFlowBindingOverrides": {},
      "fullScopeAllowed": true,
      "nodeReRegistrationTimeout": 0,
      "defaultClientScopes": [
        "web-origins",
        "acr",
        "roles",
        "profile",
        "basic",
        "email"
      ],
      "optionalClientScopes": [
        "address",
        "phone",
        "organization",
        "offline_access",
        "microprofile-jwt"
      ]
    },
    {
      "id": "d2ba0100-17be-4c6b-8540-ebaa22b6e2e8",
      "clientId": "broker",
      "name": "${client_broker}",
      "surrogateAuthRequired": false,
      "enabled": true,
      "alwaysDisplayInConsole": false,
      "clientAuthenticatorType": "client-secret",
      "redirectUris": [],
      "webOrigins": [],
      "notBefore": 0,
      "bearerOnly": true,
      "consentRequired": false,
      "standardFlowEnabled": true,
      "implicitFlowEnabled": false,
      "directAccessGrantsEnabled": false,
      "serviceAccountsEnabled": false,
      "publicClient": false,
      "frontchannelLogout": false,
      "protocol": "openid-connect",
      "attributes": {
        "realm_client": "true"
      },
      "authenticationFlowBindingOverrides": {},
      "fullScopeAllowed": false,
      "nodeReRegistrationTimeout": 0,
      "defaultClientScopes": [
        "web-origins",
        "acr",
        "roles",
        "profile",
        "basic",
        "email"
      ],
      "optionalClientScopes": [
        "address",
        "phone",
        "organization",
        "offline_access",
        "microprofile-jwt"
      ]
    },
    {
      "id": "120ed66c-44a4-41fe-82e7-bb471f09e53e",
      "clientId": "internet-shop",
      "name": "Internet Shop",
      "description": "The client of Payment Service spring boot application",
      "rootUrl": "http://localhost:8080/",
      "adminUrl": "http://localhost:8080/",
      "baseUrl": "http://localhost:8080/catalog/items",
      "surrogateAuthRequired": false,
      "enabled": true,
      "alwaysDisplayInConsole": false,
      "clientAuthenticatorType": "client-secret",
      "secret": "kBHUpq4qgCG0tIQy78iavvOADBgCoX4o",
      "redirectUris": [
        "http://localhost:8080/*"
      ],
      "webOrigins": [
        "http://localhost:8080"
      ],
      "notBefore": 0,
      "bearerOnly": false,
      "consentRequired": false,
      "standardFlowEnabled": true,
      "implicitFlowEnabled": false,
      "directAccessGrantsEnabled": true,
      "serviceAccountsEnabled": true,
      "publicClient": false,
      "frontchannelLogout": true,
      "protocol": "openid-connect",
      "attributes": {
        "realm_client": "false",
        "oidc.ciba.grant.enabled": "false",
        "client.secret.creation.time": "1760132668",
        "backchannel.logout.session.required": "true",
        "post.logout.redirect.uris": "http://localhost:8080/catalog",
        "oauth2.device.authorization.grant.enabled": "false",
        "backchannel.logout.revoke.offline.tokens": "false"
      },
      "authenticationFlowBindingOverrides": {},
      "fullScopeAllowed": true,
      "nodeReRegistrationTimeout": -1,
      "defaultClientScopes": [
        "service_account",
        "web-origins",
        "acr",
        "roles",
        "profile",
        "basic",
        "email"
      ],
      "optionalClientScopes": [
        "address",
        "phone",
        "organization",
        "offline_access",
        "microprofile-jwt"
      ]
    },
    {
      "id": "4ba9c175-bf74-43db-9cf6-e1c1052415c6",
      "clientId": "master-realm",
      "name": "master Realm",
      "surrogateAuthRequired": false,
      "enabled": true,
      "alwaysDisplayInConsole": false,
      "clientAuthenticatorType": "client-secret",
      "redirectUris": [],
      "webOrigins": [],
      "notBefore": 0,
      "bearerOnly": true,
      "consentRequired": false,
      "standardFlowEnabled": true,
      "implicitFlowEnabled": false,
      "directAccessGrantsEnabled": false,
      "serviceAccountsEnabled": false,
      "publicClient": false,
      "frontchannelLogout": false,
      "attributes": {
        "realm_client": "true"
      },
      "authenticationFlowBindingOverrides": {},
      "fullScopeAllowed": false,
      "nodeReRegistrationTimeout": 0,
      "defaultClientScopes": [
        "web-origins",
        "acr",
        "roles",
        "profile",
        "basic",
        "email"
      ],
      "optionalClientScopes": [
        "address",
        "phone",
        "organization",
        "offline_access",
        "microprofile-jwt"
      ]
    },
    {
      "id": "80db3bac-f8a0-4970-a45f-44e4ecd0df0f",
      "clientId": "security-admin-console",
      "name": "${client_security-admin-console}",
      "rootUrl": "${authAdminUrl}",
      "baseUrl": "/admin/master/console/",
      "surrogateAuthRequired": false,
      "enabled": true,
      "alwaysDisplayInConsole": false,
      "clientAuthenticatorType": "client-secret",
      "redirectUris": [
        "/admin/master/console/*"
      ],
      "webOrigins": [
        "+"
      ],
      "notBefore": 0,
      "bearerOnly": false,
      "consentRequired": false,
      "standardFlowEnabled": true,
      "implicitFlowEnabled": false,
      "directAccessGrantsEnabled": false,
      "serviceAccountsEnabled": false,
      "publicClient": true,
      "frontchannelLogout": false,
      "protocol": "openid-connect",
      "attributes": {
        "realm_client": "false",
        "client.use.lightweight.access.token.enabled": "true",
        "post.logout.redirect.uris": "+",
        "pkce.code.challenge.method": "S256"
      },
      "authenticationFlowBindingOverrides": {},
      "fullScopeAllowed": true,
      "nodeReRegistrationTimeout": 0,
      "protocolMappers": [
        {
          "id": "79261461-5763-469d-a424-595ac436b8d8",
          "name": "locale",
          "protocol": "openid-connect",
          "protocolMapper": "oidc-usermodel-attribute-mapper",
          "consentRequired": false,
          "config": {
            "introspection.token.claim": "true",
            "userinfo.token.claim": "true",
            "user.attribute": "locale",
            "id.token.claim": "true",
            "access.token.claim": "true",
            "claim.name": "locale",
            "jsonType.label": "String"
          }
        }
      ],
      "defaultClientScopes": [
        "web-origins",
        "acr",
        "roles",
        "profile",
        "basic",
        "email"
      ],
      "optionalClientScopes": [
        "address",
        "phone",
        "organization",
        "offline_access",
        "microprofile-jwt"
      ]
    }
  ],
  "clientScopes": [
    {
      "id": "169c40f8-5063-4d16-9a8a-248794d5ca6a",
      "name": "offline_access",
      "description": "OpenID Connect built-in scope: offline_access",
      "protocol": "openid-connect",
      "attributes": {
        "consent.screen.text": "${offlineAccessScopeConsentText}",
        "display.on.consent.screen": "true"
      }
    },
    {
      "id": "dd673faf-5ee0-41a8-90ad-e306346d1ee0",
      "name": "phone",
      "description": "OpenID Connect built-in scope: phone",
      "protocol": "openid-connect",
      "attributes": {
        "include.in.token.scope": "true",
        "consent.screen.text": "${phoneScopeConsentText}",
        "display.on.consent.screen": "true"
      },
      "protocolMappers": [
        {
          "id": "605ece47-e1ab-4b11-b456-eb1ab57347e7",
          "name": "phone number verified",
          "protocol": "openid-connect",
          "protocolMapper": "oidc-usermodel-attribute-mapper",
          "consentRequired": false,
          "config": {
            "introspection.token.claim": "true",
            "userinfo.token.claim": "true",
            "user.attribute": "phoneNumberVerified",
            "id.token.claim": "true",
            "access.token.claim": "true",
            "claim.name": "phone_number_verified",
            "jsonType.label": "boolean"
          }
        },
        {
          "id": "a8840211-621b-4e8b-ae17-07cfcd639eb1",
          "name": "phone number",
          "protocol": "openid-connect",
          "protocolMapper": "oidc-usermodel-attribute-mapper",
          "consentRequired": false,
          "config": {
            "introspection.token.claim": "true",
            "userinfo.token.claim": "true",
            "user.attribute": "phoneNumber",
            "id.token.claim": "true",
            "access.token.claim": "true",
            "claim.name": "phone_number",
            "jsonType.label": "String"
          }
        }
      ]
    },
    {
      "id": "c5e7559a-22a8-4a83-99b3-7bed08b717b9",
      "name": "address",
      "description": "OpenID Connect built-in scope: address",
      "protocol": "openid-connect",
      "attributes": {
        "include.in.token.scope": "true",
        "consent.screen.text": "${addressScopeConsentText}",
        "display.on.consent.screen": "true"
      },
      "protocolMappers": [
        {
          "id": "22a89978-538c-48f3-b3b2-caf5a932b01b",
          "name": "address",
          "protocol": "openid-connect",
          "protocolMapper": "oidc-address-mapper",
          "consentRequired": false,
          "config": {
            "user.attribute.formatted": "formatted",
            "user.attribute.country": "country",
            "introspection.token.claim": "true",
            "user.attribute.postal_code": "postal_code",
            "userinfo.token.claim": "true",
            "user.attribute.street": "street",
            "id.token.claim": "true",
            "user.attribute.region": "region",
            "access.token.claim": "true",
            "user.attribute.locality": "locality"
          }
        }
      ]
    },
    {
      "id": "4ca2959d-07c8-4fc9-a1e0-08524f4aa8d2",
      "name": "roles",
      "description": "OpenID Connect scope for add user roles to the access token",
      "protocol": "openid-connect",
      "attributes": {
        "include.in.token.scope": "false",
        "consent.screen.text": "${rolesScopeConsentText}",
        "display.on.consent.screen": "true"
      },
      "protocolMappers": [
        {
          "id": "eea0a931-5b85-460b-96c1-e69056470e95",
          "name": "audience resolve",
          "protocol": "openid-connect",
          "protocolMapper": "oidc-audience-resolve-mapper",
          "consentRequired": false,
          "config": {
            "introspection.token.claim": "true",
            "access.token.claim": "true"
          }
        },
        {
          "id": "1e4eebc7-b36a-44e6-b43c-a9c8b63c2b3c",
          "name": "client roles",
          "protocol": "openid-connect",
          "protocolMapper": "oidc-usermodel-client-role-mapper",
          "consentRequired": false,
          "config": {
            "user.attribute": "foo",
            "introspection.token.claim": "true",
            "access.token.claim": "true",
            "claim.name": "resource_access.${client_id}.roles",
            "jsonType.label": "String",
            "multivalued": "true"
          }
        },
        {
          "id": "e931d4fa-529a-42f5-a869-8f4e4ccd040f",
          "name": "realm roles",
          "protocol": "openid-connect",
          "protocolMapper": "oidc-usermodel-realm-role-mapper",
          "consentRequired": false,
          "config": {
            "user.attribute": "foo",
            "introspection.token.claim": "true",
            "access.token.claim": "true",
            "claim.name": "realm_access.roles",
            "jsonType.label": "String",
            "multivalued": "true"
          }
        }
      ]
    },
    {
      "id": "7a438641-ebf3-428f-a58e-25410d130a30",
      "name": "acr",
      "description": "OpenID Connect scope for add acr (authentication context class reference) to the token",
      "protocol": "openid-connect",
      "attributes": {
        "include.in.token.scope": "false",
        "display.on.consent.screen": "false"
      },
      "protocolMappers": [
        {
          "id": "7c689e53-4ca8-4e32-8d73-54af9b88582c",
          "name": "acr loa level",
          "protocol": "openid-connect",
          "protocolMapper": "oidc-acr-mapper",
          "consentRequired": false,
          "config": {
            "id.token.claim": "true",
            "introspection.token.claim": "true",
            "access.token.claim": "true"
          }
        }
      ]
    },
    {
      "id": "1fc66e14-351f-402c-8e53-00dad1de7674",
      "name": "organization",
      "description": "Additional claims about the organization a subject belongs to",
      "protocol": "openid-connect",
      "attributes": {
        "include.in.token.scope": "true",
        "consent.screen.text": "${organizationScopeConsentText}",
        "display.on.consent.screen": "true"
      },
      "protocolMappers": [
        {
          "id": "aef0599d-8fe6-4742-b8df-9825c8f67d41",
          "name": "organization",
          "protocol": "openid-connect",
          "protocolMapper": "oidc-organization-membership-mapper",
          "consentRequired": false,
          "config": {
            "id.token.claim": "true",
            "introspection.token.claim": "true",
            "access.token.claim": "true",
            "claim.name": "organization",
            "jsonType.label": "String",
            "multivalued": "true"
          }
        }
      ]
    },
    {
      "id": "6ea078a5-a5cb-4c38-91c6-b8b4067d8649",
      "name": "service_account",
      "description": "Specific scope for a client enabled for service accounts",
      "protocol": "openid-connect",
      "attributes": {
        "include.in.token.scope": "false",
        "display.on.consent.screen": "false"
      },
      "protocolMappers": [
        {
          "id": "23b2c790-5427-4a7c-a90b-93a145937600",
          "name": "Client Host",
          "protocol": "openid-connect",
          "protocolMapper": "oidc-usersessionmodel-note-mapper",
          "consentRequired": false,
          "config": {
            "user.session.note": "clientHost",
            "id.token.claim": "true",
            "introspection.token.claim": "true",
            "access.token.claim": "true",
            "claim.name": "clientHost",
            "jsonType.label": "String"
          }
        },
        {
          "id": "2f041fb1-4706-4461-b160-72be00a86fa8",
          "name": "Client IP Address",
          "protocol": "openid-connect",
          "protocolMapper": "oidc-usersessionmodel-note-mapper",
          "consentRequired": false,
          "config": {
            "user.session.note": "clientAddress",
            "id.token.claim": "true",
            "introspection.token.claim": "true",
            "access.token.claim": "true",
            "claim.name": "clientAddress",
            "jsonType.label": "String"
          }
        },
        {
          "id": "5e6fca52-fb35-48d1-a097-285536308571",
          "name": "Client ID",
          "protocol": "openid-connect",
          "protocolMapper": "oidc-usersessionmodel-note-mapper",
          "consentRequired": false,
          "config": {
            "user.session.note": "client_id",
            "id.token.claim": "true",
            "introspection.token.claim": "true",
            "access.token.claim": "true",
            "claim.name": "client_id",
            "jsonType.label": "String"
          }
        }
      ]
    },
    {
      "id": "f95da52c-28d7-49d8-bc1b-566542ecdcdd",
      "name": "email",
      "description": "OpenID Connect built-in scope: email",
      "protocol": "openid-connect",
      "attributes": {
        "include.in.token.scope": "true",
        "consent.screen.text": "${emailScopeConsentText}",
        "display.on.consent.screen": "true"
      },
      "protocolMappers": [
        {
          "id": "826262cb-3189-4ef4-8f07-71d5eb3ef219",
          "name": "email verified",
          "protocol": "openid-connect",
          "protocolMapper": "oidc-usermodel-property-mapper",
          "consentRequired": false,
          "config": {
            "introspection.token.claim": "true",
            "userinfo.token.claim": "true",
            "user.attribute": "emailVerified",
            "id.token.claim": "true",
            "access.token.claim": "true",
            "claim.name": "email_verified",
            "jsonType.label": "boolean"
          }
        },
        {
          "id": "c8f062b4-0f5d-4ec6-b5f7-c7d0ae19e253",
          "name": "email",
          "protocol": "openid-connect",
          "protocolMapper": "oidc-usermodel-attribute-mapper",
          "consentRequired": false,
          "config": {
            "introspection.token.claim": "true",
            "userinfo.token.claim": "true",
            "user.attribute": "email",
            "id.token.claim": "true",
            "access.token.claim": "true",
            "claim.name": "email",
            "jsonType.label": "String"
          }
        }
      ]
    },
    {
      "id": "276ba308-0f19-4dcd-a416-468375950e10",
      "name": "web-origins",
      "description": "OpenID Connect scope for add allowed web origins to the access token",
      "protocol": "openid-connect",
      "attributes": {
        "include.in.token.scope": "false",
        "consent.screen.text": "",
        "display.on.consent.screen": "false"
      },
      "protocolMappers": [
        {
          "id": "c990d739-eb04-4d32-9156-a7a940af8610",
          "name": "allowed web origins",
          "protocol": "openid-connect",
          "protocolMapper": "oidc-allowed-origins-mapper",
          "consentRequired": false,
          "config": {
            "introspection.token.claim": "true",
            "access.token.claim": "true"
          }
        }
      ]
    },
    {
      "id": "40dcb00d-6b40-426d-b4a7-8987b1761f04",
      "name": "basic",
      "description": "OpenID Connect scope for add all basic claims to the token",
      "protocol": "openid-connect",
      "attributes": {
        "include.in.token.scope": "false",
        "display.on.consent.screen": "false"
      },
      "protocolMappers": [
        {
          "id": "6d24b175-9679-43ea-9af5-449cc71fd657",
          "name": "sub",
          "protocol": "openid-connect",
          "protocolMapper": "oidc-sub-mapper",
          "consentRequired": false,
          "config": {
            "introspection.token.claim": "true",
            "access.token.claim": "true"
          }
        },
        {
          "id": "7f57d6fe-a936-4dc8-82d5-c1ea331ffaba",
          "name": "auth_time",
          "protocol": "openid-connect",
          "protocolMapper": "oidc-usersessionmodel-note-mapper",
          "consentRequired": false,
          "config": {
            "user.session.note": "AUTH_TIME",
            "id.token.claim": "true",
            "introspection.token.claim": "true",
            "access.token.claim": "true",
            "claim.name": "auth_time",
            "jsonType.label": "long"
          }
        }
      ]
    },
    {
      "id": "49613aa9-ab7e-468f-87c4-69ee11e42693",
      "name": "role_list",
      "description": "SAML role list",
      "protocol": "saml",
      "attributes": {
        "consent.screen.text": "${samlRoleListScopeConsentText}",
        "display.on.consent.screen": "true"
      },
      "protocolMappers": [
        {
          "id": "c5801239-1c97-4148-883d-9de9cb1fa755",
          "name": "role list",
          "protocol": "saml",
          "protocolMapper": "saml-role-list-mapper",
          "consentRequired": false,
          "config": {
            "single": "false",
            "attribute.nameformat": "Basic",
            "attribute.name": "Role"
          }
        }
      ]
    },
    {
      "id": "396a0454-9855-45c8-985f-0a18248a3e0c",
      "name": "saml_organization",
      "description": "Organization Membership",
      "protocol": "saml",
      "attributes": {
        "display.on.consent.screen": "false"
      },
      "protocolMappers": [
        {
          "id": "77817fba-f4c7-44dd-bbbd-149f4b3b048c",
          "name": "organization",
          "protocol": "saml",
          "protocolMapper": "saml-organization-membership-mapper",
          "consentRequired": false,
          "config": {}
        }
      ]
    },
    {
      "id": "eb8f6028-1698-4658-8e03-bd1aff1bd3f7",
      "name": "microprofile-jwt",
      "description": "Microprofile - JWT built-in scope",
      "protocol": "openid-connect",
      "attributes": {
        "include.in.token.scope": "true",
        "display.on.consent.screen": "false"
      },
      "protocolMappers": [
        {
          "id": "5fb096b4-3de7-49f1-88e8-a082d5fb9b4c",
          "name": "upn",
          "protocol": "openid-connect",
          "protocolMapper": "oidc-usermodel-attribute-mapper",
          "consentRequired": false,
          "config": {
            "introspection.token.claim": "true",
            "userinfo.token.claim": "true",
            "user.attribute": "username",
            "id.token.claim": "true",
            "access.token.claim": "true",
            "claim.name": "upn",
            "jsonType.label": "String"
          }
        },
        {
          "id": "81604fd5-56c3-4bfe-8bb1-8a388092a550",
          "name": "groups",
          "protocol": "openid-connect",
          "protocolMapper": "oidc-usermodel-realm-role-mapper",
          "consentRequired": false,
          "config": {
            "introspection.token.claim": "true",
            "multivalued": "true",
            "user.attribute": "foo",
            "id.token.claim": "true",
            "access.token.claim": "true",
            "claim.name": "groups",
            "jsonType.label": "String"
          }
        }
      ]
    },
    {
      "id": "36f44705-7e67-4dd9-8ac9-66c8d245f5f7",
      "name": "profile",
      "description": "OpenID Connect built-in scope: profile",
      "protocol": "openid-connect",
      "attributes": {
        "include.in.token.scope": "true",
        "consent.screen.text": "${profileScopeConsentText}",
        "display.on.consent.screen": "true"
      },
      "protocolMappers": [
        {
          "id": "bc668979-3a7c-4d0f-893e-70a32774168e",
          "name": "birthdate",
          "protocol": "openid-connect",
          "protocolMapper": "oidc-usermodel-attribute-mapper",
          "consentRequired": false,
          "config": {
            "introspection.token.claim": "true",
            "userinfo.token.claim": "true",
            "user.attribute": "birthdate",
            "id.token.claim": "true",
            "access.token.claim": "true",
            "claim.name": "birthdate",
            "jsonType.label": "String"
          }
        },
        {
          "id": "cdacd430-9399-40af-a348-0e048adda4f7",
          "name": "gender",
          "protocol": "openid-connect",
          "protocolMapper": "oidc-usermodel-attribute-mapper",
          "consentRequired": false,
          "config": {
            "introspection.token.claim": "true",
            "userinfo.token.claim": "true",
            "user.attribute": "gender",
            "id.token.claim": "true",
            "access.token.claim": "true",
            "claim.name": "gender",
            "jsonType.label": "String"
          }
        },
        {
          "id": "309ce4b8-1629-4169-b2be-f641905df0ae",
          "name": "family name",
          "protocol": "openid-connect",
          "protocolMapper": "oidc-usermodel-attribute-mapper",
          "consentRequired": false,
          "config": {
            "introspection.token.claim": "true",
            "userinfo.token.claim": "true",
            "user.attribute": "lastName",
            "id.token.claim": "true",
            "access.token.claim": "true",
            "claim.name": "family_name",
            "jsonType.label": "String"
          }
        },
        {
          "id": "5bb66a2d-5c08-4f3d-8ad3-086ddd798497",
          "name": "full name",
          "protocol": "openid-connect",
          "protocolMapper": "oidc-full-name-mapper",
          "consentRequired": false,
          "config": {
            "id.token.claim": "true",
            "introspection.token.claim": "true",
            "access.token.claim": "true",
            "userinfo.token.claim": "true"
          }
        },
        {
          "id": "1f85254f-9bf5-4d33-9099-32a0092ecd07",
          "name": "profile",
          "protocol": "openid-connect",
          "protocolMapper": "oidc-usermodel-attribute-mapper",
          "consentRequired": false,
          "config": {
            "introspection.token.claim": "true",
            "userinfo.token.claim": "true",
            "user.attribute": "profile",
            "id.token.claim": "true",
            "access.token.claim": "true",
            "claim.name": "profile",
            "jsonType.label": "String"
          }
        },
        {
          "id": "77fbf843-b04b-44e8-866f-ddde6651ece1",
          "name": "locale",
          "protocol": "openid-connect",
          "protocolMapper": "oidc-usermodel-attribute-mapper",
          "consentRequired": false,
          "config": {
            "introspection.token.claim": "true",
            "userinfo.token.claim": "true",
            "user.attribute": "locale",
            "id.token.claim": "true",
            "access.token.claim": "true",
            "claim.name": "locale",
            "jsonType.label": "String"
          }
        },
        {
          "id": "46889a6a-8f8e-4325-8029-e73659edf7d8",
          "name": "middle name",
          "protocol": "openid-connect",
          "protocolMapper": "oidc-usermodel-attribute-mapper",
          "consentRequired": false,
          "config": {
            "introspection.token.claim": "true",
            "userinfo.token.claim": "true",
            "user.attribute": "middleName",
            "id.token.claim": "true",
            "access.token.claim": "true",
            "claim.name": "middle_name",
            "jsonType.label": "String"
          }
        },
        {
          "id": "64da11c0-cdd9-488e-a99e-ded18f968f3e",
          "name": "username",
          "protocol": "openid-connect",
          "protocolMapper": "oidc-usermodel-attribute-mapper",
          "consentRequired": false,
          "config": {
            "introspection.token.claim": "true",
            "userinfo.token.claim": "true",
            "user.attribute": "username",
            "id.token.claim": "true",
            "access.token.claim": "true",
            "claim.name": "preferred_username",
            "jsonType.label": "String"
          }
        },
        {
          "id": "a6ba4c7c-0a0c-496e-a60c-d9c66e66740e",
          "name": "website",
          "protocol": "openid-connect",
          "protocolMapper": "oidc-usermodel-attribute-mapper",
          "consentRequired": false,
          "config": {
            "introspection.token.claim": "true",
            "userinfo.token.claim": "true",
            "user.attribute": "website",
            "id.token.claim": "true",
            "access.token.claim": "true",
            "claim.name": "website",
            "jsonType.label": "String"
          }
        },
        {
          "id": "fc4c24bc-2905-488d-9068-dfb56a000f8e",
          "name": "updated at",
          "protocol": "openid-connect",
          "protocolMapper": "oidc-usermodel-attribute-mapper",
          "consentRequired": false,
          "config": {
            "introspection.token.claim": "true",
            "userinfo.token.claim": "true",
            "user.attribute": "updatedAt",
            "id.token.claim": "true",
            "access.token.claim": "true",
            "claim.name": "updated_at",
            "jsonType.label": "long"
          }
        },
        {
          "id": "f8c146a1-e96a-4264-b553-dd55811ae384",
          "name": "picture",
          "protocol": "openid-connect",
          "protocolMapper": "oidc-usermodel-attribute-mapper",
          "consentRequired": false,
          "config": {
            "introspection.token.claim": "true",
            "userinfo.token.claim": "true",
            "user.attribute": "picture",
            "id.token.claim": "true",
            "access.token.claim": "true",
            "claim.name": "picture",
            "jsonType.label": "String"
          }
        },
        {
          "id": "410269ce-0af2-4e04-969d-a7a8f9d4848e",
          "name": "nickname",
          "protocol": "openid-connect",
          "protocolMapper": "oidc-usermodel-attribute-mapper",
          "consentRequired": false,
          "config": {
            "introspection.token.claim": "true",
            "userinfo.token.claim": "true",
            "user.attribute": "nickname",
            "id.token.claim": "true",
            "access.token.claim": "true",
            "claim.name": "nickname",
            "jsonType.label": "String"
          }
        },
        {
          "id": "a2c2871a-18cc-4639-8ef4-3a27a443f13f",
          "name": "given name",
          "protocol": "openid-connect",
          "protocolMapper": "oidc-usermodel-attribute-mapper",
          "consentRequired": false,
          "config": {
            "introspection.token.claim": "true",
            "userinfo.token.claim": "true",
            "user.attribute": "firstName",
            "id.token.claim": "true",
            "access.token.claim": "true",
            "claim.name": "given_name",
            "jsonType.label": "String"
          }
        },
        {
          "id": "c712a94e-561e-43c8-ad88-b8f6061fd222",
          "name": "zoneinfo",
          "protocol": "openid-connect",
          "protocolMapper": "oidc-usermodel-attribute-mapper",
          "consentRequired": false,
          "config": {
            "introspection.token.claim": "true",
            "userinfo.token.claim": "true",
            "user.attribute": "zoneinfo",
            "id.token.claim": "true",
            "access.token.claim": "true",
            "claim.name": "zoneinfo",
            "jsonType.label": "String"
          }
        }
      ]
    }
  ],
  "defaultDefaultClientScopes": [
    "role_list",
    "saml_organization",
    "profile",
    "email",
    "roles",
    "web-origins",
    "acr",
    "basic"
  ],
  "defaultOptionalClientScopes": [
    "offline_access",
    "address",
    "phone",
    "microprofile-jwt",
    "organization"
  ],
  "browserSecurityHeaders": {
    "contentSecurityPolicyReportOnly": "",
    "xContentTypeOptions": "nosniff",
    "referrerPolicy": "no-referrer",
    "xRobotsTag": "none",
    "xFrameOptions": "SAMEORIGIN",
    "contentSecurityPolicy": "frame-src 'self'; frame-ancestors 'self'; object-src 'none';",
    "xXSSProtection": "1; mode=block",
    "strictTransportSecurity": "max-age=31536000; includeSubDomains"
  },
  "smtpServer": {},
  "eventsEnabled": false,
  "eventsListeners": [
    "jboss-logging"
  ],
  "enabledEventTypes": [],
  "adminEventsEnabled": false,
  "adminEventsDetailsEnabled": false,
  "identityProviders": [],
  "identityProviderMappers": [],
  "components": {
    "org.keycloak.services.clientregistration.policy.ClientRegistrationPolicy": [
      {
        "id": "d5a56c9d-c6e5-4fd9-a888-8c3217aecf78",
        "name": "Allowed Client Scopes",
        "providerId": "allowed-client-templates",
        "subType": "anonymous",
        "subComponents": {},
        "config": {
          "allow-default-scopes": [
            "true"
          ]
        }
      },
      {
        "id": "121e16a1-0963-4ae5-a59c-ee79ea8955d1",
        "name": "Allowed Protocol Mapper Types",
        "providerId": "allowed-protocol-mappers",
        "subType": "authenticated",
        "subComponents": {},
        "config": {
          "allowed-protocol-mapper-types": [
            "saml-user-property-mapper",
            "oidc-sha256-pairwise-sub-mapper",
            "oidc-full-name-mapper",
            "oidc-usermodel-property-mapper",
            "oidc-address-mapper",
            "saml-user-attribute-mapper",
            "oidc-usermodel-attribute-mapper",
            "saml-role-list-mapper"
          ]
        }
      },
      {
        "id": "af436353-a17d-4492-8afe-5f03586bfed4",
        "name": "Full Scope Disabled",
        "providerId": "scope",
        "subType": "anonymous",
        "subComponents": {},
        "config": {}
      },
      {
        "id": "76dceee0-1fbe-4aeb-bf92-1bba04ec9a51",
        "name": "Max Clients Limit",
        "providerId": "max-clients",
        "subType": "anonymous",
        "subComponents": {},
        "config": {
          "max-clients": [
            "200"
          ]
        }
      },
      {
        "id": "6b2669e3-bee9-4d79-baf6-dd8bbd3fc620",
        "name": "Consent Required",
        "providerId": "consent-required",
        "subType": "anonymous",
        "subComponents": {},
        "config": {}
      },
      {
        "id": "956bf1ac-8b22-4c64-b55c-6eb50573b4c1",
        "name": "Allowed Client Scopes",
        "providerId": "allowed-client-templates",
        "subType": "authenticated",
        "subComponents": {},
        "config": {
          "allow-default-scopes": [
            "true"
          ]
        }
      },
      {
        "id": "577151b7-ba94-4d7b-9ecd-80d7b09f5f69",
        "name": "Trusted Hosts",
        "providerId": "trusted-hosts",
        "subType": "anonymous",
        "subComponents": {},
        "config": {
          "host-sending-registration-request-must-match": [
            "true"
          ],
          "client-uris-must-match": [
            "true"
          ]
        }
      },
      {
        "id": "4c119f74-2868-407b-ba7b-d67a56c31c59",
        "name": "Allowed Protocol Mapper Types",
        "providerId": "allowed-protocol-mappers",
        "subType": "anonymous",
        "subComponents": {},
        "config": {
          "allowed-protocol-mapper-types": [
            "oidc-usermodel-property-mapper",
            "saml-role-list-mapper",
            "saml-user-attribute-mapper",
            "oidc-sha256-pairwise-sub-mapper",
            "oidc-usermodel-attribute-mapper",
            "oidc-address-mapper",
            "saml-user-property-mapper",
            "oidc-full-name-mapper"
          ]
        }
      }
    ],
    "org.keycloak.userprofile.UserProfileProvider": [
      {
        "id": "840b3a63-7c2c-41ce-97a1-eb33fc238fef",
        "providerId": "declarative-user-profile",
        "subComponents": {},
        "config": {
          "kc.user.profile.config": [
            "{\"attributes\":[{\"name\":\"username\",\"displayName\":\"${username}\",\"validations\":{\"length\":{\"min\":3,\"max\":255},\"username-prohibited-characters\":{},\"up-username-not-idn-homograph\":{}},\"permissions\":{\"view\":[\"admin\",\"user\"],\"edit\":[\"admin\",\"user\"]},\"multivalued\":false},{\"name\":\"email\",\"displayName\":\"${email}\",\"validations\":{\"email\":{},\"length\":{\"max\":255}},\"permissions\":{\"view\":[\"admin\",\"user\"],\"edit\":[\"admin\",\"user\"]},\"multivalued\":false},{\"name\":\"firstName\",\"displayName\":\"${firstName}\",\"validations\":{\"length\":{\"max\":255},\"person-name-prohibited-characters\":{}},\"permissions\":{\"view\":[\"admin\",\"user\"],\"edit\":[\"admin\",\"user\"]},\"multivalued\":false},{\"name\":\"lastName\",\"displayName\":\"${lastName}\",\"validations\":{\"length\":{\"max\":255},\"person-name-prohibited-characters\":{}},\"permissions\":{\"view\":[\"admin\",\"user\"],\"edit\":[\"admin\",\"user\"]},\"multivalued\":false}],\"groups\":[{\"name\":\"user-metadata\",\"displayHeader\":\"User metadata\",\"displayDescription\":\"Attributes, which refer to user metadata\"}]}"
          ]
        }
      }
    ],
    "org.keycloak.keys.KeyProvider": [
      {
        "id": "1e581b42-72d9-463d-b535-df3078a5cf47",
        "name": "aes-generated",
        "providerId": "aes-generated",
        "subComponents": {},
        "config": {
          "priority": [
            "100"
          ]
        }
      },
      {
        "id": "a0c29628-6d64-4ac0-84e4-066a554f25b1",
        "name": "rsa-generated",
        "providerId": "rsa-generated",
        "subComponents": {},
        "config": {
          "priority": [
            "100"
          ]
        }
      },
      {
        "id": "911eb454-4073-4136-b2c8-08078ee97cbe",
        "name": "rsa-enc-generated",
        "providerId": "rsa-enc-generated",
        "subComponents": {},
        "config": {
          "priority": [
            "100"
          ],
          "algorithm": [
            "RSA-OAEP"
          ]
        }
      },
      {
        "id": "6ac5123a-6171-4475-8a9e-3d977b8d149f",
        "name": "hmac-generated-hs512",
        "providerId": "hmac-generated",
        "subComponents": {},
        "config": {
          "priority": [
            "100"
          ],
          "algorithm": [
            "HS512"
          ]
        }
      }
    ]
  },
  "internationalizationEnabled": false,
  "supportedLocales": [],
  "authenticationFlows": [
    {
      "id": "7f213d97-7e1d-4850-b9dd-7a9196e27c32",
      "alias": "Account verification options",
      "description": "Method with which to verity the existing account",
      "providerId": "basic-flow",
      "topLevel": false,
      "builtIn": true,
      "authenticationExecutions": [
        {
          "authenticator": "idp-email-verification",
          "authenticatorFlow": false,
          "requirement": "ALTERNATIVE",
          "priority": 10,
          "autheticatorFlow": false,
          "userSetupAllowed": false
        },
        {
          "authenticatorFlow": true,
          "requirement": "ALTERNATIVE",
          "priority": 20,
          "autheticatorFlow": true,
          "flowAlias": "Verify Existing Account by Re-authentication",
          "userSetupAllowed": false
        }
      ]
    },
    {
      "id": "5ea0c80e-b376-4280-9950-e4792c95266b",
      "alias": "Browser - Conditional OTP",
      "description": "Flow to determine if the OTP is required for the authentication",
      "providerId": "basic-flow",
      "topLevel": false,
      "builtIn": true,
      "authenticationExecutions": [
        {
          "authenticator": "conditional-user-configured",
          "authenticatorFlow": false,
          "requirement": "REQUIRED",
          "priority": 10,
          "autheticatorFlow": false,
          "userSetupAllowed": false
        },
        {
          "authenticator": "auth-otp-form",
          "authenticatorFlow": false,
          "requirement": "REQUIRED",
          "priority": 20,
          "autheticatorFlow": false,
          "userSetupAllowed": false
        }
      ]
    },
    {
      "id": "38ead13b-3b4e-4441-9dfc-b9fa7f5a50f5",
      "alias": "Direct Grant - Conditional OTP",
      "description": "Flow to determine if the OTP is required for the authentication",
      "providerId": "basic-flow",
      "topLevel": false,
      "builtIn": true,
      "authenticationExecutions": [
        {
          "authenticator": "conditional-user-configured",
          "authenticatorFlow": false,
          "requirement": "REQUIRED",
          "priority": 10,
          "autheticatorFlow": false,
          "userSetupAllowed": false
        },
        {
          "authenticator": "direct-grant-validate-otp",
          "authenticatorFlow": false,
          "requirement": "REQUIRED",
          "priority": 20,
          "autheticatorFlow": false,
          "userSetupAllowed": false
        }
      ]
    },
    {
      "id": "e01a5b64-ceec-4ab1-8da1-e9be6a17f796",
      "alias": "First broker login - Conditional OTP",
      "description": "Flow to determine if the OTP is required for the authentication",
      "providerId": "basic-flow",
      "topLevel": false,
      "builtIn": true,
      "authenticationExecutions": [
        {
          "authenticator": "conditional-user-configured",
          "authenticatorFlow": false,
          "requirement": "REQUIRED",
          "priority": 10,
          "autheticatorFlow": false,
          "userSetupAllowed": false
        },
        {
          "authenticator": "auth-otp-form",
          "authenticatorFlow": false,
          "requirement": "REQUIRED",
          "priority": 20,
          "autheticatorFlow": false,
          "userSetupAllowed": false
        }
      ]
    },
    {
      "id": "39145f49-d9f1-4011-8529-1e6b78e7bdef",
      "alias": "Handle Existing Account",
      "description": "Handle what to do if there is existing account with same email/username like authenticated identity provider",
      "providerId": "basic-flow",
      "topLevel": false,
      "builtIn": true,
      "authenticationExecutions": [
        {
          "authenticator": "idp-confirm-link",
          "authenticatorFlow": false,
          "requirement": "REQUIRED",
          "priority": 10,
          "autheticatorFlow": false,
          "userSetupAllowed": false
        },
        {
          "authenticatorFlow": true,
          "requirement": "REQUIRED",
          "priority": 20,
          "autheticatorFlow": true,
          "flowAlias": "Account verification options",
          "userSetupAllowed": false
        }
      ]
    },
    {
      "id": "9b424b5b-c2ba-467b-92d7-00a6afcadffe",
      "alias": "Reset - Conditional OTP",
      "description": "Flow to determine if the OTP should be reset or not. Set to REQUIRED to force.",
      "providerId": "basic-flow",
      "topLevel": false,
      "builtIn": true,
      "authenticationExecutions": [
        {
          "authenticator": "conditional-user-configured",
          "authenticatorFlow": false,
          "requirement": "REQUIRED",
          "priority": 10,
          "autheticatorFlow": false,
          "userSetupAllowed": false
        },
        {
          "authenticator": "reset-otp",
          "authenticatorFlow": false,
          "requirement": "REQUIRED",
          "priority": 20,
          "autheticatorFlow": false,
          "userSetupAllowed": false
        }
      ]
    },
    {
      "id": "6865f2c2-0a49-4bf2-9759-ebfef1a89fe3",
      "alias": "User creation or linking",
      "description": "Flow for the existing/non-existing user alternatives",
      "providerId": "basic-flow",
      "topLevel": false,
      "builtIn": true,
      "authenticationExecutions": [
        {
          "authenticatorConfig": "create unique user config",
          "authenticator": "idp-create-user-if-unique",
          "authenticatorFlow": false,
          "requirement": "ALTERNATIVE",
          "priority": 10,
          "autheticatorFlow": false,
          "userSetupAllowed": false
        },
        {
          "authenticatorFlow": true,
          "requirement": "ALTERNATIVE",
          "priority": 20,
          "autheticatorFlow": true,
          "flowAlias": "Handle Existing Account",
          "userSetupAllowed": false
        }
      ]
    },
    {
      "id": "ea680178-ee6e-48d3-9b6d-59a10791eb34",
      "alias": "Verify Existing Account by Re-authentication",
      "description": "Reauthentication of existing account",
      "providerId": "basic-flow",
      "topLevel": false,
      "builtIn": true,
      "authenticationExecutions": [
        {
          "authenticator": "idp-username-password-form",
          "authenticatorFlow": false,
          "requirement": "REQUIRED",
          "priority": 10,
          "autheticatorFlow": false,
          "userSetupAllowed": false
        },
        {
          "authenticatorFlow": true,
          "requirement": "CONDITIONAL",
          "priority": 20,
          "autheticatorFlow": true,
          "flowAlias": "First broker login - Conditional OTP",
          "userSetupAllowed": false
        }
      ]
    },
    {
      "id": "2ac02859-c27c-4caf-9699-978835bcb8f6",
      "alias": "browser",
      "description": "Browser based authentication",
      "providerId": "basic-flow",
      "topLevel": true,
      "builtIn": true,
      "authenticationExecutions": [
        {
          "authenticator": "auth-cookie",
          "authenticatorFlow": false,
          "requirement": "ALTERNATIVE",
          "priority": 10,
          "autheticatorFlow": false,
          "userSetupAllowed": false
        },
        {
          "authenticator": "auth-spnego",
          "authenticatorFlow": false,
          "requirement": "DISABLED",
          "priority": 20,
          "autheticatorFlow": false,
          "userSetupAllowed": false
        },
        {
          "authenticator": "identity-provider-redirector",
          "authenticatorFlow": false,
          "requirement": "ALTERNATIVE",
          "priority": 25,
          "autheticatorFlow": false,
          "userSetupAllowed": false
        },
        {
          "authenticatorFlow": true,
          "requirement": "ALTERNATIVE",
          "priority": 30,
          "autheticatorFlow": true,
          "flowAlias": "forms",
          "userSetupAllowed": false
        }
      ]
    },
    {
      "id": "b708ec7f-166c-404e-a3ae-d0c7db4055cd",
      "alias": "clients",
      "description": "Base authentication for clients",
      "providerId": "client-flow",
      "topLevel": true,
      "builtIn": true,
      "authenticationExecutions": [
        {
          "authenticator": "client-secret",
          "authenticatorFlow": false,
          "requirement": "ALTERNATIVE",
          "priority": 10,
          "autheticatorFlow": false,
          "userSetupAllowed": false
        },
        {
          "authenticator": "client-jwt",
          "authenticatorFlow": false,
          "requirement": "ALTERNATIVE",
          "priority": 20,
          "autheticatorFlow": false,
          "userSetupAllowed": false
        },
        {
          "authenticator": "client-secret-jwt",
          "authenticatorFlow": false,
          "requirement": "ALTERNATIVE",
          "priority": 30,
          "autheticatorFlow": false,
          "userSetupAllowed": false
        },
        {
          "authenticator": "client-x509",
          "authenticatorFlow": false,
          "requirement": "ALTERNATIVE",
          "priority": 40,
          "autheticatorFlow": false,
          "userSetupAllowed": false
        }
      ]
    },
    {
      "id": "3e04fa9a-d1c4-449b-9794-a759081ab416",
      "alias": "direct grant",
      "description": "OpenID Connect Resource Owner Grant",
      "providerId": "basic-flow",
      "topLevel": true,
      "builtIn": true,
      "authenticationExecutions": [
        {
          "authenticator": "direct-grant-validate-username",
          "authenticatorFlow": false,
          "requirement": "REQUIRED",
          "priority": 10,
          "autheticatorFlow": false,
          "userSetupAllowed": false
        },
        {
          "authenticator": "direct-grant-validate-password",
          "authenticatorFlow": false,
          "requirement": "REQUIRED",
          "priority": 20,
          "autheticatorFlow": false,
          "userSetupAllowed": false
        },
        {
          "authenticatorFlow": true,
          "requirement": "CONDITIONAL",
          "priority": 30,
          "autheticatorFlow": true,
          "flowAlias": "Direct Grant - Conditional OTP",
          "userSetupAllowed": false
        }
      ]
    },
    {
      "id": "0d5e7ed3-6418-4783-9772-984e2641fffc",
      "alias": "docker auth",
      "description": "Used by Docker clients to authenticate against the IDP",
      "providerId": "basic-flow",
      "topLevel": true,
      "builtIn": true,
      "authenticationExecutions": [
        {
          "authenticator": "docker-http-basic-authenticator",
          "authenticatorFlow": false,
          "requirement": "REQUIRED",
          "priority": 10,
          "autheticatorFlow": false,
          "userSetupAllowed": false
        }
      ]
    },
    {
      "id": "bb5313da-63a0-49ed-99b6-237953fd5fad",
      "alias": "first broker login",
      "description": "Actions taken after first broker login with identity provider account, which is not yet linked to any Keycloak account",
      "providerId": "basic-flow",
      "topLevel": true,
      "builtIn": true,
      "authenticationExecutions": [
        {
          "authenticatorConfig": "review profile config",
          "authenticator": "idp-review-profile",
          "authenticatorFlow": false,
          "requirement": "REQUIRED",
          "priority": 10,
          "autheticatorFlow": false,
          "userSetupAllowed": false
        },
        {
          "authenticatorFlow": true,
          "requirement": "REQUIRED",
          "priority": 20,
          "autheticatorFlow": true,
          "flowAlias": "User creation or linking",
          "userSetupAllowed": false
        }
      ]
    },
    {
      "id": "da1b6feb-c9f0-47f7-897b-2653b6f884fb",
      "alias": "forms",
      "description": "Username, password, otp and other auth forms.",
      "providerId": "basic-flow",
      "topLevel": false,
      "builtIn": true,
      "authenticationExecutions": [
        {
          "authenticator": "auth-username-password-form",
          "authenticatorFlow": false,
          "requirement": "REQUIRED",
          "priority": 10,
          "autheticatorFlow": false,
          "userSetupAllowed": false
        },
        {
          "authenticatorFlow": true,
          "requirement": "CONDITIONAL",
          "priority": 20,
          "autheticatorFlow": true,
          "flowAlias": "Browser - Conditional OTP",
          "userSetupAllowed": false
        }
      ]
    },
    {
      "id": "2395c5a0-9544-4769-8bc5-7438d7b47dc5",
      "alias": "registration",
      "description": "Registration flow",
      "providerId": "basic-flow",
      "topLevel": true,
      "builtIn": true,
      "authenticationExecutions": [
        {
          "authenticator": "registration-page-form",
          "authenticatorFlow": true,
          "requirement": "REQUIRED",
          "priority": 10,
          "autheticatorFlow": true,
          "flowAlias": "registration form",
          "userSetupAllowed": false
        }
      ]
    },
    {
      "id": "f7e22df8-42d4-4637-8e75-e5e601c0d91c",
      "alias": "registration form",
      "description": "Registration form",
      "providerId": "form-flow",
      "topLevel": false,
      "builtIn": true,
      "authenticationExecutions": [
        {
          "authenticator": "registration-user-creation",
          "authenticatorFlow": false,
          "requirement": "REQUIRED",
          "priority": 20,
          "autheticatorFlow": false,
          "userSetupAllowed": false
        },
        {
          "authenticator": "registration-password-action",
          "authenticatorFlow": false,
          "requirement": "REQUIRED",
          "priority": 50,
          "autheticatorFlow": false,
          "userSetupAllowed": false
        },
        {
          "authenticator": "registration-recaptcha-action",
          "authenticatorFlow": false,
          "requirement": "DISABLED",
          "priority": 60,
          "autheticatorFlow": false,
          "userSetupAllowed": false
        },
        {
          "authenticator": "registration-terms-and-conditions",
          "authenticatorFlow": false,
          "requirement": "DISABLED",
          "priority": 70,
          "autheticatorFlow": false,
          "userSetupAllowed": false
        }
      ]
    },
    {
      "id": "299322bb-51ba-408c-a3ec-f8b911e50d08",
      "alias": "reset credentials",
      "description": "Reset credentials for a user if they forgot their password or something",
      "providerId": "basic-flow",
      "topLevel": true,
      "builtIn": true,
      "authenticationExecutions": [
        {
          "authenticator": "reset-credentials-choose-user",
          "authenticatorFlow": false,
          "requirement": "REQUIRED",
          "priority": 10,
          "autheticatorFlow": false,
          "userSetupAllowed": false
        },
        {
          "authenticator": "reset-credential-email",
          "authenticatorFlow": false,
          "requirement": "REQUIRED",
          "priority": 20,
          "autheticatorFlow": false,
          "userSetupAllowed": false
        },
        {
          "authenticator": "reset-password",
          "authenticatorFlow": false,
          "requirement": "REQUIRED",
          "priority": 30,
          "autheticatorFlow": false,
          "userSetupAllowed": false
        },
        {
          "authenticatorFlow": true,
          "requirement": "CONDITIONAL",
          "priority": 40,
          "autheticatorFlow": true,
          "flowAlias": "Reset - Conditional OTP",
          "userSetupAllowed": false
        }
      ]
    },
    {
      "id": "b886b599-25cb-4f67-b6e1-8d7dc2708319",
      "alias": "saml ecp",
      "description": "SAML ECP Profile Authentication Flow",
      "providerId": "basic-flow",
      "topLevel": true,
      "builtIn": true,
      "authenticationExecutions": [
        {
          "authenticator": "http-basic-authenticator",
          "authenticatorFlow": false,
          "requirement": "REQUIRED",
          "priority": 10,
          "autheticatorFlow": false,
          "userSetupAllowed": false
        }
      ]
    }
  ],
  "authenticatorConfig": [
    {
      "id": "66f7c858-750f-41cd-a686-fa9a55a58a4e",
      "alias": "create unique user config",
      "config": {
        "require.password.update.after.registration": "false"
      }
    },
    {
      "id": "fbfd69c9-8f95-492f-b2d9-48fe732b507a",
      "alias": "review profile config",
      "config": {
        "update.profile.on.first.login": "missing"
      }
    }
  ],
  "requiredActions": [
    {
      "alias": "CONFIGURE_TOTP",
      "name": "Configure OTP",
      "providerId": "CONFIGURE_TOTP",
      "enabled": true,
      "defaultAction": false,
      "priority": 10,
      "config": {}
    },
    {
      "alias": "TERMS_AND_CONDITIONS",
      "name": "Terms and Conditions",
      "providerId": "TERMS_AND_CONDITIONS",
      "enabled": false,
      "defaultAction": false,
      "priority": 20,
      "config": {}
    },
    {
      "alias": "UPDATE_PASSWORD",
      "name": "Update Password",
      "providerId": "UPDATE_PASSWORD",
      "enabled": true,
      "defaultAction": false,
      "priority": 30,
      "config": {}
    },
    {
      "alias": "UPDATE_PROFILE",
      "name": "Update Profile",
      "providerId": "UPDATE_PROFILE",
      "enabled": true,
      "defaultAction": false,
      "priority": 40,
      "config": {}
    },
    {
      "alias": "VERIFY_EMAIL",
      "name": "Verify Email",
      "providerId": "VERIFY_EMAIL",
      "enabled": true,
      "defaultAction": false,
      "priority": 50,
      "config": {}
    },
    {
      "alias": "delete_account",
      "name": "Delete Account",
      "providerId": "delete_account",
      "enabled": false,
      "defaultAction": false,
      "priority": 60,
      "config": {}
    },
    {
      "alias": "webauthn-register",
      "name": "Webauthn Register",
      "providerId": "webauthn-register",
      "enabled": true,
      "defaultAction": false,
      "priority": 70,
      "config": {}
    },
    {
      "alias": "webauthn-register-passwordless",
      "name": "Webauthn Register Passwordless",
      "providerId": "webauthn-register-passwordless",
      "enabled": true,
      "defaultAction": false,
      "priority": 80,
      "config": {}
    },
    {
      "alias": "VERIFY_PROFILE",
      "name": "Verify Profile",
      "providerId": "VERIFY_PROFILE",
      "enabled": true,
      "defaultAction": false,
      "priority": 90,
      "config": {}
    },
    {
      "alias": "delete_credential",
      "name": "Delete Credential",
      "providerId": "delete_credential",
      "enabled": true,
      "defaultAction": false,
      "priority": 100,
      "config": {}
    },
    {
      "alias": "update_user_locale",
      "name": "Update User Locale",
      "providerId": "update_user_locale",
      "enabled": true,
      "defaultAction": false,
      "priority": 1000,
      "config": {}
    }
  ],
  "browserFlow": "browser",
  "registrationFlow": "registration",
  "directGrantFlow": "direct grant",
  "resetCredentialsFlow": "reset credentials",
  "clientAuthenticationFlow": "clients",
  "dockerAuthenticationFlow": "docker auth",
  "firstBrokerLoginFlow": "first broker login",
  "attributes": {
    "cibaBackchannelTokenDeliveryMode": "poll",
    "cibaExpiresIn": "120",
    "cibaAuthRequestedUserHint": "login_hint",
    "parRequestUriLifespan": "60",
    "cibaInterval": "5",
    "realmReusableOtpCode": "false"
  },
  "keycloakVersion": "26.1.3",
  "userManagedAccessAllowed": false,
  "organizationsEnabled": false,
  "verifiableCredentialsEnabled": false,
  "adminPermissionsEnabled": false,
  "clientProfiles": {
    "profiles": []
  },
  "clientPolicies": {
    "policies": []
  }
}